s_aes/__init__.py
s_aes/cli.py
s_aes/core.py
s_aes_util-0.2.0.dist-info/METADATA
s_aes_util-0.2.0.dist-info/WHEEL
s_aes_util-0.2.0.dist-info/entry_points.txt
s_aes_util-0.2.0.dist-info/top_level.txt
s_aes_util-0.2.0.dist-info/RECORD
