Metadata-Version: 2.4
Name: s-aes-util
Version: 0.2.0
Summary: A simple implementation of the Simplified AES (S-AES) encryption algorithm
Author-email: A Guy <myemailisprivate@gmail.com>
